pactman/__init__.py
pactman/__main__.py
pactman/__version__.py
pactman/mock/__init__.py
pactman/mock/consumer.py
pactman/mock/matchers.py
pactman/mock/mock_server.py
pactman/mock/mock_urlopen.py
pactman/mock/pact.py
pactman/mock/pact_request_handler.py
pactman/mock/provider.py
pactman/mock/publish.py
pactman/mock/request.py
pactman/mock/response.py
pactman/test/__init__.py
pactman/test/exercise_sample.py
pactman/test/test_matching_rules.py
pactman/test/test_mock_consumer.py
pactman/test/test_mock_pact.py
pactman/test/test_mock_server.py
pactman/test/test_mock_urlopen.py
pactman/test/test_pact_generation.py
pactman/test/test_parse_header.py
pactman/test/test_pytest_plugin.py
pactman/test/test_result.py
pactman/test/test_verifier.py
pactman/test/mock_matchers/__init__.py
pactman/test/mock_matchers/test_eachlike.py
pactman/test/mock_matchers/test_equality.py
pactman/test/mock_matchers/test_headers.py
pactman/test/mock_matchers/test_include.py
pactman/test/mock_matchers/test_like.py
pactman/test/mock_matchers/test_mock_matchers.py
pactman/test/mock_matchers/test_non_json.py
pactman/test/mock_matchers/test_term.py
pactman/test/pact_serialisation/__init__.py
pactman/test/pact_serialisation/test_body.py
pactman/test/pact_serialisation/test_full_payload.py
pactman/test/pact_serialisation/test_given.py
pactman/test/pact_serialisation/test_header.py
pactman/test/pact_serialisation/test_path.py
pactman/test/pact_serialisation/test_request_query.py
pactman/verifier/__init__.py
pactman/verifier/broker_pact.py
pactman/verifier/command_line.py
pactman/verifier/matching_rule.py
pactman/verifier/parse_header.py
pactman/verifier/paths.py
pactman/verifier/pytest_plugin.py
pactman/verifier/result.py
pactman/verifier/verify.py
pactman_patched-2.30.2.dist-info/LICENSE
pactman_patched-2.30.2.dist-info/METADATA
pactman_patched-2.30.2.dist-info/WHEEL
pactman_patched-2.30.2.dist-info/entry_points.txt
pactman_patched-2.30.2.dist-info/top_level.txt
pactman_patched-2.30.2.dist-info/RECORD
