Metadata-Version: 2.1
Name: pactman-patched
Version: 2.30.2
Summary: Tools for creating and verifying consumer driven contracts using the Pact framework.
Home-page: https://github.com/panargirakis/pactman
Author: Panos Argyrakis
Author-email: panargirakis@gmail.com
License: MIT, Copyright (c) 2018 ReeceTech
Platform: UNKNOWN
Classifier: Intended Audience :: Developers
Classifier: License :: OSI Approved :: MIT License
Classifier: Programming Language :: Python :: 3
Classifier: Programming Language :: Python :: 3.7
Classifier: Programming Language :: Python :: 3.8
Classifier: Programming Language :: Python :: 3.9
Classifier: Topic :: Software Development :: Testing
Classifier: Topic :: Software Development :: Testing :: Mocking
Classifier: Topic :: Software Development :: Testing :: Acceptance
License-File: LICENSE
Requires-Dist: pytest
Requires-Dist: requests
Requires-Dist: semver
Requires-Dist: colorama
Requires-Dist: restnavigator
